LICENSE.txt
MANIFEST.in
README.md
setup.cfg
setup.py
examples/example1.xpdt
test/test_decode.py
test/test_enums.py
test/test_nested.py
test/test_parser.py
test/test_roundtrip.py
test/test_stringy.py
xpdt/__init__.py
xpdt/__main__.py
xpdt/__version__.py
xpdt/basetypes.py
xpdt/buftypes.py
xpdt/c.py
xpdt/decl.py
xpdt/dupes.py
xpdt/integraltype.py
xpdt/intstack.py
xpdt/jinja.py
xpdt/lex.py
xpdt/load.py
xpdt/member.py
xpdt/namespace.py
xpdt/parse.py
xpdt/py.typed
xpdt/registry.py
xpdt/shiftreduce.py
xpdt/struct.py
xpdt/symbology.py
xpdt/type.py
xpdt/typedef.py
xpdt/uuidtype.py
xpdt.egg-info/PKG-INFO
xpdt.egg-info/SOURCES.txt
xpdt.egg-info/dependency_links.txt
xpdt.egg-info/entry_points.txt
xpdt.egg-info/requires.txt
xpdt.egg-info/top_level.txt
xpdt/templates/__init__.py
xpdt/templates/api.c
xpdt/templates/apihdr.c
xpdt/templates/fixed.pyt
xpdt/templates/macros.c
xpdt/templates/vbuf.pyt
xpdt/templates/xpdt.c
xpdt/templates/xpdt.pyt
xpdt/templates/__pycache__/__init__.cpython-311.pyc
xpdt/templates/__pycache__/__init__.cpython-312.pyc